[
  {
    "src": "/images/thai-health.png",
    "alt": "สำนักงานกองทุนสนับสนุนการสร้างเสริมสุขภาพ"
  },
  {
    "src": "/images/labour.png",
    "alt": "กรมสวัสดิการและคุ้มครองแรงงาน"
  },
  {
    "src": "/images/public health.png",
    "alt": "กรมอนามัย"
  },
  {
    "src": "/images/thai-health.png",
    "alt": "สำนักงานกองทุนสนับสนุนการสร้างเสริมสุขภาพ"
  },
  {
    "src": "/images/public health.png",
    "alt": "กรมอนามัย"
  },
  {
    "src": "/images/thai-health.png",
    "alt": "สำนักงานกองทุนสนับสนุนการสร้างเสริมสุขภาพ"
  },
  {
    "src": "/images/public health.png",
    "alt": "กรมอนามัย"
  }
]
